{
  "objectInfo" : {
    "id" : "6CN8SjAufo9bMU5x1aStK9",
    "name" : "Profile",
    "type" : "PROFILE",
    "metadata" : {
      "modelVersion" : {
        "major" : 1,
        "minor" : 0
      },
      "repoInfo" : {
        "repoHandle" : "9506ec5f-eeee-4ea0-b728-1e8aba2ca8db"
      },
      "contextAttributes" : [ ],
      "additionalInfo" : {
        "description" : null,
        "contentType" : null,
        "documentState" : "VALID"
      }
    }
  },
  "dataFileExtension" : "json",
  "updateTime" : "2025-02-07T13:46:32.194Z",
  "objectRefs" : [ {
    "id" : "hznHG8SFbEul7FaHzEnw0N",
    "name" : "ORA_SRC",
    "type" : "Connection",
    "metadata" : {
      "modelVersion" : {
        "major" : 0,
        "minor" : 0
      },
      "repoInfo" : {
        "repoHandle" : "011F0V0B000000000002"
      },
      "contextAttributes" : null,
      "additionalInfo" : {
        "description" : null,
        "contentType" : "JSON",
        "documentState" : "COMPLETE"
      }
    },
    "path" : "/SYS"
  } ],
  "readableFileExtension" : null,
  "readableFilePresent" : false
}